pytest_richer/__init__.py
pytest_richer/compat.py
pytest_richer/header.py
pytest_richer/helpers.py
pytest_richer/plugin.py
pytest_richer/progress.py
pytest_richer/reporting.py
pytest_richer/terminal.py
pytest_richer-0.1.1.dist-info/LICENSE
pytest_richer-0.1.1.dist-info/METADATA
pytest_richer-0.1.1.dist-info/WHEEL
pytest_richer-0.1.1.dist-info/entry_points.txt
pytest_richer-0.1.1.dist-info/top_level.txt
pytest_richer-0.1.1.dist-info/RECORD
