Metadata-Version: 2.1
Name: pytest-richer
Version: 0.1.1
Summary: Pytest plugin providing a Rich based reporter.
Author-email: Paul Ollis <paul@cleversheep.org>
Project-URL: Homepage, https://github.com/paul-ollis/pytest-richer
Project-URL: Bug Tracker, https://github.com/paul-ollis/pytest-richer/issues
Classifier: Development Status :: 3 - Alpha
Classifier: Environment :: Console
Classifier: Framework :: Pytest
Classifier: License :: OSI Approved :: MIT License
Classifier: Operating System :: Microsoft :: Windows
Classifier: Operating System :: POSIX :: Linux
Classifier: Programming Language :: Python :: 3
Classifier: Programming Language :: Python :: 3.11
Classifier: Programming Language :: Python :: 3.12
Requires-Python: >=3.11
License-File: LICENSE
Requires-Dist: rich
Requires-Dist: pytest
